odoo/addons/sale_line_returned_qty/README.rst
odoo/addons/sale_line_returned_qty/__init__.py
odoo/addons/sale_line_returned_qty/__manifest__.py
odoo/addons/sale_line_returned_qty/i18n/fr_CA.po
odoo/addons/sale_line_returned_qty/i18n/fr_FR.po
odoo/addons/sale_line_returned_qty/i18n/it.po
odoo/addons/sale_line_returned_qty/i18n/sale_line_returned_qty.pot
odoo/addons/sale_line_returned_qty/models/__init__.py
odoo/addons/sale_line_returned_qty/models/sale_order_line.py
odoo/addons/sale_line_returned_qty/readme/CONTRIBUTORS.rst
odoo/addons/sale_line_returned_qty/readme/DESCRIPTION.rst
odoo/addons/sale_line_returned_qty/static/description/icon.png
odoo/addons/sale_line_returned_qty/static/description/index.html
odoo/addons/sale_line_returned_qty/tests/__init__.py
odoo/addons/sale_line_returned_qty/tests/test_sale_line_returned_qty.py
odoo/addons/sale_line_returned_qty/views/sale_order_views.xml
odoo14_addon_sale_line_returned_qty-14.0.1.0.1.dev8.dist-info/METADATA
odoo14_addon_sale_line_returned_qty-14.0.1.0.1.dev8.dist-info/WHEEL
odoo14_addon_sale_line_returned_qty-14.0.1.0.1.dev8.dist-info/top_level.txt
odoo14_addon_sale_line_returned_qty-14.0.1.0.1.dev8.dist-info/RECORD
